unraphael/__init__.py
unraphael/cli.py
unraphael/feature.py
unraphael/io.py
unraphael/locations.py
unraphael/pose.py
unraphael/preprocess.py
unraphael/dash/__init__.py
unraphael/dash/config.py
unraphael/dash/home.py
unraphael/dash/image_sim.py
unraphael/dash/packages.txt
unraphael/dash/readme.md
unraphael/dash/requirements.txt
unraphael/dash/styling.py
unraphael/dash/widgets.py
unraphael/dash/.streamlit/config.toml
unraphael/dash/pages/1_preprocess.py
unraphael/dash/pages/2_image_similarity.py
unraphael/dash/pages/3_detect_objects.py
unraphael/data/__init__.py
unraphael/data/config.yaml
unraphael/data/custom.css
unraphael/data/logo-dark.png
unraphael/data/logo.png
unraphael/data/images/0_edinburgh_nat_gallery.jpg
unraphael/data/images/10_nolay_maison_retraite.jpg
unraphael/data/images/1_london_nat_gallery.jpg
unraphael/data/images/2_naples_museo_capodimonte.jpg
unraphael/data/images/3_milan_private.jpg
unraphael/data/images/4_oxford_ashmolean.jpg
unraphael/data/images/5_uk_nostrell_priory.jpg
unraphael/data/images/6_oxford_christ_church.jpg
unraphael/data/images/7_uk_warrington_museum.jpg
unraphael/data/images/8_london_order_st-john.jpg
unraphael/data/images/9_zurich_kuny_collection.jpg
unraphael-0.2.1.dist-info/LICENSE
unraphael-0.2.1.dist-info/METADATA
unraphael-0.2.1.dist-info/WHEEL
unraphael-0.2.1.dist-info/entry_points.txt
unraphael-0.2.1.dist-info/top_level.txt
unraphael-0.2.1.dist-info/RECORD
