Metadata-Version: 2.1
Name: unraphael
Version: 0.2.1
Summary: Decoding Raphael: Computational Study of the Production and Reproduction of Italian Renaissance Paintings.
Author-email: Thijs Vroegh <t.vroegh@esciencecenter.nl>
License: MIT License
Project-URL: homepage, https://github.com/DecodingRaphael/unraphael
Project-URL: issues, https://github.com/DecodingRaphael/unraphael/issues
Project-URL: documentation, https://unraphael.readthedocs.io
Project-URL: changelog, https://github.com/DecodingRaphael/unraphael/releases
Keywords: art,raphael,computer-vision,renaissance
Classifier: Development Status :: 3 - Alpha
Classifier: Intended Audience :: Science/Research
Classifier: License :: OSI Approved :: MIT License
Classifier: Natural Language :: English
Classifier: Programming Language :: Python :: 3
Classifier: Programming Language :: Python :: 3.10
Classifier: Programming Language :: Python :: 3.11
Classifier: Programming Language :: Python :: 3.12
Classifier: Topic :: Scientific/Engineering :: Image Processing
Requires-Python: >=3.10
License-File: LICENSE
Requires-Dist: numpy
Requires-Dist: rembg
Requires-Dist: scikit-image
Requires-Dist: scipy
Requires-Dist: PyYAML
Provides-Extra: dash
Requires-Dist: seaborn ; extra == 'dash'
Requires-Dist: streamlit ; extra == 'dash'
Provides-Extra: develop
Requires-Dist: bump-my-version ; extra == 'develop'
Requires-Dist: ruff ; extra == 'develop'
Requires-Dist: pre-commit ; extra == 'develop'
Requires-Dist: coverage[toml] ; extra == 'develop'
Requires-Dist: pytest ; extra == 'develop'
Requires-Dist: pycodestyle ; extra == 'develop'
Provides-Extra: docs
Requires-Dist: markdown-include ; extra == 'docs'
Requires-Dist: mkdocs ; extra == 'docs'
Requires-Dist: mkdocs-material ; extra == 'docs'
Requires-Dist: mkdocstrings[python] ; extra == 'docs'
Provides-Extra: publishing
Requires-Dist: twine ; extra == 'publishing'
Requires-Dist: wheel ; extra == 'publishing'
Requires-Dist: build ; extra == 'publishing'
